hpcmagic/__init__.py
hpcmagic/custom.js
hpcmagic/hpcmagic.ini
hpcmagic/hpcmagic.py
hpcmagic/ipython_config.py
compiler_magics-1.0.1.dist-info/LICENSE.txt
compiler_magics-1.0.1.dist-info/METADATA
compiler_magics-1.0.1.dist-info/WHEEL
compiler_magics-1.0.1.dist-info/top_level.txt
compiler_magics-1.0.1.dist-info/RECORD
