Metadata-Version: 2.1
Name: compiler-magics
Version: 1.0.1
Summary: Distributing a custom cell magic to do compilation
Home-page: https://github.com/drtpotter/compiler_magics
Author: Dr Toby Potter
Author-email: tobympotter@gmail.com
License: UNKNOWN
Project-URL: Bug Reports, https://github.com/drtpotter/compiler_magics/issues
Project-URL: Funding, https://www.pelagos-consulting.com
Project-URL: Source, https://github.com/drtpotter/compiler_magics
Keywords: cell magic jupyter
Platform: UNKNOWN
Classifier: Development Status :: 3 - Alpha
Classifier: Intended Audience :: Developers
Classifier: Topic :: Software Development :: Build Tools
Classifier: License :: OSI Approved :: GNU General Public License v3 (GPLv3)
Classifier: Programming Language :: Python :: 3
Requires-Python: >=3.3
License-File: LICENSE.txt
Requires-Dist: jupyter
